lifehacks/metaclasses/__init__.py
lifehacks/metaclasses/__main__.py
lifehacks/metaclasses/enum.py
lifehacks/metaclasses/enum.pyi
lifehacks/metaclasses/exceptions.py
lifehacks/metaclasses/meta.py
lifehacks/metaclasses/meta.pyi
lifehacks/metaclasses/metadeco.py
lifehacks/metaclasses/metadeco.pyi
lifehacks/metaclasses/py.typed
lifehacks.metaclasses-1.2.4.dist-info/LICENSE.md
lifehacks.metaclasses-1.2.4.dist-info/METADATA
lifehacks.metaclasses-1.2.4.dist-info/WHEEL
lifehacks.metaclasses-1.2.4.dist-info/top_level.txt
lifehacks.metaclasses-1.2.4.dist-info/RECORD
